otlpy/__init__.py
otlpy/py.typed
otlpy/base/__init__.py
otlpy/base/account.py
otlpy/base/crypto.py
otlpy/base/market.py
otlpy/base/net.py
otlpy/base/util.py
otlpy/binance/__init__.py
otlpy/binance/api.py
otlpy/binance/common.py
otlpy/binance/settings.py
otlpy/binance/spot.py
otlpy/kis/__init__.py
otlpy/kis/api.py
otlpy/kis/common.py
otlpy/kis/domestic_stock.py
otlpy/kis/settings.py
otlpy-0.0.4.dist-info/LICENSE
otlpy-0.0.4.dist-info/WHEEL
otlpy-0.0.4.dist-info/METADATA
otlpy-0.0.4.dist-info/RECORD
